LICENSE
MANIFEST.in
README.md
README.rst
setup.py
viz/__init__.py
viz/cli.py
viz/format.py
viz/geom.py
viz/gloss.py
viz/stats.py
viz/terminal.py
viz/text.py
viz.egg-info/PKG-INFO
viz.egg-info/SOURCES.txt
viz.egg-info/dependency_links.txt
viz.egg-info/entry_points.txt
viz.egg-info/requires.txt
viz.egg-info/top_level.txt