Metadata-Version: 1.1
Name: viz
Version: 0.0.5
Summary: Data visualization in the terminal
Home-page: https://github.com/chbrown/viz
Author: Christopher Brown
Author-email: io@henrian.com
License: Copyright (c) 2013 Christopher Brown
